playwright_mcp_server/__init__.py
playwright_mcp_server/main.py
playwright_mcp_server/playwrightHandler.py
tests/__init__.py
tests/test_server.py
playwright_mcp_server-0.1.0.dist-info/LICENSE
playwright_mcp_server-0.1.0.dist-info/METADATA
playwright_mcp_server-0.1.0.dist-info/WHEEL
playwright_mcp_server-0.1.0.dist-info/entry_points.txt
playwright_mcp_server-0.1.0.dist-info/top_level.txt
playwright_mcp_server-0.1.0.dist-info/RECORD
