Metadata-Version: 2.1
Name: playwright-mcp-server
Version: 0.1.0
Summary: MCP server exposing Playwright browser automation capabilities
Home-page: https://github.com/yourusername/playwright-mcp-server
Author: HA
Author-email: ha30.coding1@gmail.com
Classifier: Programming Language :: Python :: 3
Classifier: License :: OSI Approved :: MIT License
Classifier: Operating System :: OS Independent
Requires-Python: >=3.8
License-File: LICENSE
Requires-Dist: playwright
Requires-Dist: mcp
Requires-Dist: asyncio
Requires-Dist: uv
Requires-Dist: mcp[cli]
